isl.py
isl_python-0.1.8.data/data/lib/libisl.so
isl_python-0.1.8.data/data/lib/libisl.so.23
isl_python-0.1.8.data/data/lib/libisl.so.23.3.0
isl_python-0.1.8.dist-info/METADATA
isl_python-0.1.8.dist-info/WHEEL
isl_python-0.1.8.dist-info/top_level.txt
isl_python-0.1.8.dist-info/RECORD
isl_python-0.1.8.dist-info/licenses/AUTHORS
isl_python-0.1.8.dist-info/licenses/LICENSE
