Metadata-Version: 2.4
Name: isl-python
Version: 0.1.8
Summary: Python binding for ISL library
Author: ZhengQiHang
Author-email: 597323109@qq.com
Maintainer: ZhengQiHang
Maintainer-email: 597323109@qq.com
License: MIT License (MIT)
Project-URL: homepage, https://github.com/zhen8838/isl
Keywords: Polyhedral,Integer Set Library
Classifier: Programming Language :: C
Classifier: Programming Language :: Python :: 3
Classifier: Programming Language :: Python :: 3.9
Classifier: Programming Language :: Python :: 3.10
Classifier: Programming Language :: Python :: 3.11
Classifier: Programming Language :: Python :: 3.12
Classifier: Operating System :: OS Independent
Requires-Python: >=3.9
License-File: LICENSE
License-File: AUTHORS
Dynamic: license-file
